spiderwws/__init__.py
spiderwws/www.py
spiderwws-0.0.2.dist-info/LICENSE
spiderwws-0.0.2.dist-info/METADATA
spiderwws-0.0.2.dist-info/WHEEL
spiderwws-0.0.2.dist-info/top_level.txt
spiderwws-0.0.2.dist-info/RECORD
